kgraphmemory/__init__.py
kgraphmemory/kginteraction_graph.py
kgraphmemory/kgraph.py
kgraphmemory/kgraph_memory.py
kgraphmemory/kgresult_list.py
kgraphmemory/kgresult_match.py
kgraphmemory/kgstatus.py
kgraphmemory/entitymodel/__init__.py
kgraphmemory/entitymodel/entitymodel.py
kgraphmemory/entitymodel/spacy_en_core_web_model.py
kgraphmemory/utils/__init__.py
kgraphmemory/utils/uri_generator.py
kgraphmemory-0.0.7.dist-info/LICENSE
kgraphmemory-0.0.7.dist-info/METADATA
kgraphmemory-0.0.7.dist-info/WHEEL
kgraphmemory-0.0.7.dist-info/top_level.txt
kgraphmemory-0.0.7.dist-info/RECORD
