Metadata-Version: 2.1
Name: kgraphmemory
Version: 0.0.7
Summary: KGraph Memory
Home-page: https://github.com/vital-ai/kgraphmemory
Author: Marc Hadfield
Author-email: marc@vital.ai
License: Apache License 2.0
Classifier: Programming Language :: Python :: 3.10
Classifier: License :: OSI Approved :: Apache Software License
Classifier: Operating System :: OS Independent
Requires-Python: >=3.10
License-File: LICENSE
Requires-Dist: vital-ai-vitalsigns>=0.1.27
Requires-Dist: vital-ai-domain>=0.1.6
Requires-Dist: six
Requires-Dist: pyyaml
Requires-Dist: vital-ai-haley-kg>=0.1.4
Requires-Dist: rdflib==7.0.0
Requires-Dist: SPARQLWrapper>=2.0.0
Requires-Dist: networkx
Requires-Dist: matplotlib
Requires-Dist: kgraphservice>=0.0.7
Requires-Dist: scikit-learn
Requires-Dist: scipy
Requires-Dist: numpy
